odoo/addons/pingen_env/README.rst
odoo/addons/pingen_env/__init__.py
odoo/addons/pingen_env/__manifest__.py
odoo/addons/pingen_env/i18n/it.po
odoo/addons/pingen_env/i18n/pingen_env.pot
odoo/addons/pingen_env/models/__init__.py
odoo/addons/pingen_env/models/res_company.py
odoo/addons/pingen_env/readme/CONFIGURE.rst
odoo/addons/pingen_env/readme/CONTRIBUTORS.rst
odoo/addons/pingen_env/readme/DESCRIPTION.rst
odoo/addons/pingen_env/readme/USAGE.rst
odoo/addons/pingen_env/static/description/icon.png
odoo/addons/pingen_env/static/description/index.html
odoo_addon_pingen_env-16.0.1.0.0.4.dist-info/METADATA
odoo_addon_pingen_env-16.0.1.0.0.4.dist-info/WHEEL
odoo_addon_pingen_env-16.0.1.0.0.4.dist-info/top_level.txt
odoo_addon_pingen_env-16.0.1.0.0.4.dist-info/RECORD
