Metadata-Version: 2.1
Name: odoo-addon-pingen_env
Version: 16.0.1.0.0.4
Summary: pingen.com server environment
Home-page: https://github.com/OCA/report-print-send
Author: Camptocamp,Odoo Community Association (OCA)
Author-email: support@odoo-community.org
License: AGPL-3
Classifier: Programming Language :: Python
Classifier: Framework :: Odoo
Classifier: Framework :: Odoo :: 16.0
Classifier: License :: OSI Approved :: GNU Affero General Public License v3
Requires-Python: >=3.10
Requires-Dist: odoo-addon-pingen <16.1dev,>=16.0dev
Requires-Dist: odoo-addon-server-environment <16.1dev,>=16.0dev
Requires-Dist: odoo <16.1dev,>=16.0a
